.gitignore
LICENSE
MANIFEST.in
README.md
setup.py
async4s/__init__.py
async4s.egg-info/PKG-INFO
async4s.egg-info/SOURCES.txt
async4s.egg-info/dependency_links.txt
async4s.egg-info/top_level.txt
async4s/m_w/__init__.py
async4s/m_w/coroutine.py
async4s/m_w/process.py
async4s/m_w/thread.py
async4s/p_c/__init__.py
async4s/p_c/coroutine.py
async4s/p_c/process.py
async4s/p_c/thread.py