Metadata-Version: 2.1
Name: async4s
Version: 2.4.0
Summary: This module makes it simplely to run things in async.
Home-page: https://github.com/meanstrong/async4s
Author: Rocky Peng
Author-email: rockypengchina@outlook.com
Maintainer: Rocky Peng
Maintainer-email: rockypengchina@outlook.com
License: Apache 2.0
Platform: any
Classifier: Programming Language :: Python
Classifier: Programming Language :: Python :: 3
